bitwarden/__init__.py
bitwarden/agent.py
bitwarden/client.py
bitwarden/crypto.py
bitwarden/db.py
bitwarden/main.py
bitwarden/slab.py
bitwarden-0.4.0.dist-info/METADATA
bitwarden-0.4.0.dist-info/RECORD
bitwarden-0.4.0.dist-info/WHEEL
bitwarden-0.4.0.dist-info/dependency_links.txt
bitwarden-0.4.0.dist-info/entry_points.txt
bitwarden-0.4.0.dist-info/top_level.txt
