Metadata-Version: 2.1
Name: bitwarden
Version: 0.4.0
Summary: Cross Platform Bitwarden library and CLI with sudolikeaboss.
Home-page: https://fossil.birl.ca/bitwarden-cli/doc/trunk/README.txt
Author: Birl.org developers
Author-email: bitwarden@birl.org
License: MIT
Platform: UNKNOWN
Classifier: License :: OSI Approved :: MIT License
Classifier: Programming Language :: Python :: 3
Requires-Dist: attrs (==17.4.0)
Requires-Dist: certifi (==2018.1.18)
Requires-Dist: click (==6.7)
Requires-Dist: click-log (==0.2.1)
Requires-Dist: cryptography (==2.2.2)
Requires-Dist: psutil (==5.4.3)
Requires-Dist: pystandardpaths (==0.3.2)
Requires-Dist: python-daemon (==2.1.2)
Requires-Dist: records (==0.5.2)
Requires-Dist: requests (==2.18.4)
Requires-Dist: tablib (==0.12.1)
Requires-Dist: web.py (==0.40.dev1)
